{
    "_hash": "47785d77d577c43ba9317c41c0cab8fdbdaae4b280a0ca08f89f64c9ff9cd6f6",
    "patches": {
        "drupal/core": [
            {
                "package": "drupal/core",
                "description": "BigPipe undefined array key fix (https://www.drupal.org/project/drupal/issues/3194462)",
                "url": "patches/bigpipe-undefined-array-key-3194462.patch",
                "sha256": "fb86aba2e2ddeaa19939cb49687b372fe22d73928e305a0a7f90655f87bb9942",
                "depth": 2,
                "extra": {
                    "provenance": "root"
                }
            }
        ],
        "drupal/tmgmt": [
            {
                "package": "drupal/tmgmt",
                "description": "Fix paragraphs asymmetric translation saving source instead of translated text (https://www.drupal.org/project/tmgmt/issues/3134922)",
                "url": "https://www.drupal.org/files/issues/2025-01-20/3134922-46.patch",
                "sha256": "af7bb76c3d94cf201fcf9d11f6a3ab704df0713a15baca020157140b0b677043",
                "depth": 1,
                "extra": {
                    "provenance": "root"
                }
            }
        ]
    }
}
